{
  "title": "北角玉帶環腰風水 — 咩係玉帶環腰？點睇你係咪住緊好風水？",
  "category": "feng-shui",
  "slug": "北角玉帶環腰風水",
  "publishedAt": "2026-06-24",
  "image": "/images/site/sunny_door1.jpg",
  "contentHtml": "<p>有客人住<strong>北角</strong>，問 Sunny 師傅：「裝修師傅話我哋屋苑係<strong>玉帶環腰</strong>（有人寫玉環帶腰），係咪一定旺財？」其實呢個係好經典嘅巒頭格局，但<strong>唔係北角每一幢樓都有</strong>，更加唔係有彎路就等於好風水。呢篇用淺白方式講清楚。</p>\n\n<h2>咩係玉帶環腰（玉環帶腰）？</h2>\n<p>風水上有名嘅「<strong>玉帶環腰</strong>」，意思係：屋企前面有一條<strong>彎曲嘅路或水</strong>，弧形<strong>內彎</strong>，像一條玉帶攬住你間屋 — 古人官服腰帶鑲玉，象徵富貴，所以叫玉帶環腰。</p>\n<p>現代城市入面，「水」多數係<strong>馬路、天橋、迴旋處</strong>。路彎內側抱屋，理論上<strong>聚氣、利財運</strong>，亦有利公職、升遷、得上司賞識嘅說法。</p>\n<p>同一個彎，如果弧形<strong>向外凸、背住你間屋</strong>，就變成<strong>反弓煞</strong> — 破財、是非，完全相反。所以唔可以只見到「有條彎路」就開心。</p>\n\n<h2>北角有冇玉帶環腰？</h2>\n<p>北角臨海、山多路彎，部分屋苑確實有「被路或海灣环抱」嘅感覺，例如靠山臨海、弧形行車道環繞平台一帶。但要睇<strong>你單位嘅層數、窗向、條彎路係內抱定外反</strong>，先可以講係咪真玉帶。</p>\n<p>相反，北角亦有不少單位面對<strong>英皇道</strong>等長直快車路 — 呢啲係氣流直沖為主，<strong>唔係</strong>玉帶環腰；要分開睇。</p>\n\n<h2>有玉帶環腰就一定好？</h2>\n<p>唔一定。師傅通常會一併睇：</p>\n<ul>\n<li><strong>彎路距離</strong> — 太近、太貼窗，可能有聲煞、割腳，氣急反而不是溫柔环抱</li>\n<li><strong>樓層</strong> — 同一座，高層同低層見到嘅「水形」可以唔同</li>\n<li><strong>反弓定环抱</strong> — 彎嘅方向決定吉凶</li>\n<li><strong>屋宅運盤、大門方位</strong> — 巒頭靚，宅運盤唔配合都未必發揮到</li>\n<li><strong>個人命盤</strong> — 風水係輔助，你嘅財帛、官祿宮先係根本</li>\n</ul>\n<p>所以裝修師傅一句「玉帶環腰」只係起點，值得搵師傅上門或帶圖<strong>實地睇過</strong>。</p>\n\n<h2>玉帶環腰最怕咩？</h2>\n<ul>\n<li>彎路變成<strong>反弓</strong></li>\n<li>貼近<strong>高速公路、天橋底</strong> — 聲煞、氣急</li>\n<li>低層被路「勒住」 — 有壓迫感</li>\n<li>只信外形，唔睇<strong>大門、廚房、睡房</strong>方位</li>\n</ul>\n\n<h2>住北角點樣知道自己係咪好風水？</h2>\n<ol>\n<li>站在客廳、睡房窗邊，睇外面道路係<strong>环抱定反弓</strong></li>\n<li>影相記錄馬路走向，預約師傅<a href=\"/booking\">風水陽宅</a>（按實用面積計費）</li>\n<li>配合<a href=\"/chart\">紫微排盤</a>睇個人財運、事業宮 — 風水同命盤一齊睇先完整</li>\n</ol>\n<p>更多家居風水可睇學堂<a href=\"/academy/feng-shui\">Sunny 談風水</a>；上次講過<a href=\"/academy/feng-shui/天鵝與鴛鴦-屋企唔好放鴛鴦\">天鵝與鴛鴦擺設</a>，都係住家常見問題。</p>\n\n<h2>師傅一句</h2>\n<p><strong>玉帶環腰係靚格，但北角唔係間間都中。</strong>彎路要攬住你，唔係劈住你；巒頭要靚，命盤都要靚，先至叫做真正住到好風水樓。</p>\n<p>— Sunny 師傅 · Destiny Home · 灣仔駱克道382號1807室（服務全港陽宅風水）</p>"
}
